igeSdk.cp39-win_amd64.pyd
igeSdk-0.1.0.dist-info/LICENSE
igeSdk-0.1.0.dist-info/METADATA
igeSdk-0.1.0.dist-info/WHEEL
igeSdk-0.1.0.dist-info/top_level.txt
igeSdk-0.1.0.dist-info/RECORD
